star_of_africa/__init__.py
star_of_africa/play.py
star_of_africa/game/__init__.py
star_of_africa/game/board_layout.py
star_of_africa/game/cities.py
star_of_africa/game/players.py
star_of_africa/game/roads.py
star_of_africa-0.0.1.dist-info/LICENSE
star_of_africa-0.0.1.dist-info/METADATA
star_of_africa-0.0.1.dist-info/WHEEL
star_of_africa-0.0.1.dist-info/top_level.txt
star_of_africa-0.0.1.dist-info/RECORD
